Workbook

Sheet How to Use
B2: MATH 243 (Statistics (descriptive) part part) — TF Practice Tracker
B3: Every Stat-part question in MATH 243 All Merged Questions.pdf (22 batch = MATH 243 (22 batch).pdf), mapped to the note file and lesson that teaches it.
B5: Workflow — after you finish a note file
B6: 1. Open its tab | C6: Tabs 1–5 follow the order of your note files. Q No. runs lesson by lesson, newest year first inside each lesson.
B7: 2. Filter | C7: Use the filter arrow on Priority → ★★★ High first (2019-20 onward). Then ★★ Medium, then ★ Low.
B8: 3. Solve | C8: Open MATH 243 All Merged Questions.pdf (22 batch = MATH 243 (22 batch).pdf) at the TF Page shown. Solve on paper under exam time (≈1.5 min per mark). Do not read the note solution first.
B9: 4. Check | C9: In Notes tells you what the note has: ✔ Solved = same question worked out; ◐ Method = method / model answer you can apply; ○ Partly = notes cover most of it, finish the rest yourself.
B10: 5. Record | C10: Tick Done, pick Confidence, add the Date. Write mistakes in My Notes. Re-solve every 'Weak' row before the exam.
B11: 6. Repeats | C11: 'Same Type Also In' lists other papers with the same question type. Solve one, then try a repeat cold — that is the real test.
B13: Columns you edit (all others are fixed data)
B14: Done (col N) | C14: TRUE / FALSE. In Google Sheets: select N4 downward → Insert → Checkbox. The values stay; ticking turns the row green.
B15: Confidence (col O) | C15: Dropdown: Weak / OK / Strong. Weak rows turn the cell red.
B16: Date (col P) | C16: Date you solved it, e.g. 16-Oct-2026.
B17: My Notes (col Q) | C17: Mistakes, missing steps, formula you forgot.
B19: Legend
B20: ★★★ High | C20: Asked in 2019-20 or later (most important — current question style).
B21: ★★ Medium | C21: Older paper, but the same question type appears at least twice in TF.
B22: ★ Low | C22: Older paper, asked once.
B23: Type | C23: Numerical = calculation · Trace = tables / step-by-step simulation · Design = construct / draw · Proof = prove / disprove · Theory = explain.
B24: Course | C24: MATH 243 = current code; MATH 245 (2016-17 to 2021-22) and MATH 241 (2011-12 to 2015-16) = old Complex Variables & Statistics papers — only their statistics/probability parts are listed.
B25: Topic | C25: Note lesson title — slide PDF and slide numbers.

Sheet Dashboard
A1: Progress Dashboard
A2: Updates automatically when you tick Done / set Confidence in tabs 1–5.
A4: # | B4: Note file (tab) | C4: Questions | D4: Done | E4: % Done | F4: Marks (total) | G4: Marks done | H4: High-priority left | I4: Weak | J4: Next unsolved (top of tab)
A5: 1 | B5: 1 Intro + Graphs | C5: =COUNTA('1 Intro + Graphs'!$E$4:$E$8) | D5: =COUNTIF('1 Intro + Graphs'!$N$4:$N$8,TRUE()) | E5: =IF(C5=0,0,D5/C5) | F5: =SUM('1 Intro + Graphs'!$H$4:$H$8) | G5: =SUMIF('1 Intro + Graphs'!$N$4:$N$8,TRUE(),'1 Intro + Graphs'!$H$4:$H$8) | H5: =COUNTIFS('1 Intro + Graphs'!$J$4:$J$8,"★★★ High",'1 Intro + Graphs'!$N$4:$N$8,FALSE()) | I5: =COUNTIF('1 Intro + Graphs'!$O$4:$O$8,"Weak") | J5: =IFERROR("Q"&INDEX('1 Intro + Graphs'!$A$4:$A$8,MATCH(FALSE(),'1 Intro + Graphs'!$N$4:$N$8,0))&" · "&INDEX('1 Intro + Graphs'!$B$4:$B$8,MATCH(FALSE(),'1 Intro + Graphs'!$N$4:$N$8,0))&" "&INDEX('1 Intro + Graphs'!$D$4:$D$8,MATCH(FALSE(),'1 Intro + Graphs'!$N$4:$N$8,0))&" · TF p."&INDEX('1 Intro + Graphs'!$I$4:$I$8,MATCH(FALSE(),'1 Intro + Graphs'!$N$4:$N$8,0)),"All done ✔")
A6: 2 | B6: 2 Central Tendency | C6: =COUNTA('2 Central Tendency'!$E$4:$E$6) | D6: =COUNTIF('2 Central Tendency'!$N$4:$N$6,TRUE()) | E6: =IF(C6=0,0,D6/C6) | F6: =SUM('2 Central Tendency'!$H$4:$H$6) | G6: =SUMIF('2 Central Tendency'!$N$4:$N$6,TRUE(),'2 Central Tendency'!$H$4:$H$6) | H6: =COUNTIFS('2 Central Tendency'!$J$4:$J$6,"★★★ High",'2 Central Tendency'!$N$4:$N$6,FALSE()) | I6: =COUNTIF('2 Central Tendency'!$O$4:$O$6,"Weak") | J6: =IFERROR("Q"&INDEX('2 Central Tendency'!$A$4:$A$6,MATCH(FALSE(),'2 Central Tendency'!$N$4:$N$6,0))&" · "&INDEX('2 Central Tendency'!$B$4:$B$6,MATCH(FALSE(),'2 Central Tendency'!$N$4:$N$6,0))&" "&INDEX('2 Central Tendency'!$D$4:$D$6,MATCH(FALSE(),'2 Central Tendency'!$N$4:$N$6,0))&" · TF p."&INDEX('2 Central Tendency'!$I$4:$I$6,MATCH(FALSE(),'2 Central Tendency'!$N$4:$N$6,0)),"All done ✔")
A7: 3 | B7: 3 Dispersion | C7: =COUNTA('3 Dispersion'!$E$4:$E$11) | D7: =COUNTIF('3 Dispersion'!$N$4:$N$11,TRUE()) | E7: =IF(C7=0,0,D7/C7) | F7: =SUM('3 Dispersion'!$H$4:$H$11) | G7: =SUMIF('3 Dispersion'!$N$4:$N$11,TRUE(),'3 Dispersion'!$H$4:$H$11) | H7: =COUNTIFS('3 Dispersion'!$J$4:$J$11,"★★★ High",'3 Dispersion'!$N$4:$N$11,FALSE()) | I7: =COUNTIF('3 Dispersion'!$O$4:$O$11,"Weak") | J7: =IFERROR("Q"&INDEX('3 Dispersion'!$A$4:$A$11,MATCH(FALSE(),'3 Dispersion'!$N$4:$N$11,0))&" · "&INDEX('3 Dispersion'!$B$4:$B$11,MATCH(FALSE(),'3 Dispersion'!$N$4:$N$11,0))&" "&INDEX('3 Dispersion'!$D$4:$D$11,MATCH(FALSE(),'3 Dispersion'!$N$4:$N$11,0))&" · TF p."&INDEX('3 Dispersion'!$I$4:$I$11,MATCH(FALSE(),'3 Dispersion'!$N$4:$N$11,0)),"All done ✔")
A8: 4 | B8: 4 Skewness + Moments | C8: =COUNTA('4 Skewness + Moments'!$E$4:$E$15) | D8: =COUNTIF('4 Skewness + Moments'!$N$4:$N$15,TRUE()) | E8: =IF(C8=0,0,D8/C8) | F8: =SUM('4 Skewness + Moments'!$H$4:$H$15) | G8: =SUMIF('4 Skewness + Moments'!$N$4:$N$15,TRUE(),'4 Skewness + Moments'!$H$4:$H$15) | H8: =COUNTIFS('4 Skewness + Moments'!$J$4:$J$15,"★★★ High",'4 Skewness + Moments'!$N$4:$N$15,FALSE()) | I8: =COUNTIF('4 Skewness + Moments'!$O$4:$O$15,"Weak") | J8: =IFERROR("Q"&INDEX('4 Skewness + Moments'!$A$4:$A$15,MATCH(FALSE(),'4 Skewness + Moments'!$N$4:$N$15,0))&" · "&INDEX('4 Skewness + Moments'!$B$4:$B$15,MATCH(FALSE(),'4 Skewness + Moments'!$N$4:$N$15,0))&" "&INDEX('4 Skewness + Moments'!$D$4:$D$15,MATCH(FALSE(),'4 Skewness + Moments'!$N$4:$N$15,0))&" · TF p."&INDEX('4 Skewness + Moments'!$I$4:$I$15,MATCH(FALSE(),'4 Skewness + Moments'!$N$4:$N$15,0)),"All done ✔")
A9: 5 | B9: 5 Correlation + Regression | C9: =COUNTA('5 Correlation + Regression'!$E$4:$E$18) | D9: =COUNTIF('5 Correlation + Regression'!$N$4:$N$18,TRUE()) | E9: =IF(C9=0,0,D9/C9) | F9: =SUM('5 Correlation + Regression'!$H$4:$H$18) | G9: =SUMIF('5 Correlation + Regression'!$N$4:$N$18,TRUE(),'5 Correlation + Regression'!$H$4:$H$18) | H9: =COUNTIFS('5 Correlation + Regression'!$J$4:$J$18,"★★★ High",'5 Correlation + Regression'!$N$4:$N$18,FALSE()) | I9: =COUNTIF('5 Correlation + Regression'!$O$4:$O$18,"Weak") | J9: =IFERROR("Q"&INDEX('5 Correlation + Regression'!$A$4:$A$18,MATCH(FALSE(),'5 Correlation + Regression'!$N$4:$N$18,0))&" · "&INDEX('5 Correlation + Regression'!$B$4:$B$18,MATCH(FALSE(),'5 Correlation + Regression'!$N$4:$N$18,0))&" "&INDEX('5 Correlation + Regression'!$D$4:$D$18,MATCH(FALSE(),'5 Correlation + Regression'!$N$4:$N$18,0))&" · TF p."&INDEX('5 Correlation + Regression'!$I$4:$I$18,MATCH(FALSE(),'5 Correlation + Regression'!$N$4:$N$18,0)),"All done ✔")
B10: TOTAL | C10: =SUM(C5:C9) | D10: =SUM(D5:D9) | E10: =IF(C10=0,0,D10/C10) | F10: =SUM(F5:F9) | G10: =SUM(G5:G9) | H10: =SUM(H5:H9) | I10: =SUM(I5:I9)
A12: Questions by year (tabs 1–5)
A13: # | B13: Year | C13: Questions | D13: Done | E13: % Done | F13: Marks (total)
A14: 1 | B14: 2023-24 | C14: =COUNTIF('1 Intro + Graphs'!$B$4:$B$8,$B14)+COUNTIF('2 Central Tendency'!$B$4:$B$6,$B14)+COUNTIF('3 Dispersion'!$B$4:$B$11,$B14)+COUNTIF('4 Skewness + Moments'!$B$4:$B$15,$B14)+COUNTIF('5 Correlation + Regression'!$B$4:$B$18,$B14) | D14: =COUNTIFS('1 Intro + Graphs'!$B$4:$B$8,$B14,'1 Intro + Graphs'!$N$4:$N$8,TRUE())+COUNTIFS('2 Central Tendency'!$B$4:$B$6,$B14,'2 Central Tendency'!$N$4:$N$6,TRUE())+COUNTIFS('3 Dispersion'!$B$4:$B$11,$B14,'3 Dispersion'!$N$4:$N$11,TRUE())+COUNTIFS('4 Skewness + Moments'!$B$4:$B$15,$B14,'4 Skewness + Moments'!$N$4:$N$15,TRUE())+COUNTIFS('5 Correlation + Regression'!$B$4:$B$18,$B14,'5 Correlation + Regression'!$N$4:$N$18,TRUE()) | E14: =IF(C14=0,0,D14/C14) | F14: =SUMIF('1 Intro + Graphs'!$B$4:$B$8,$B14,'1 Intro + Graphs'!$H$4:$H$8)+SUMIF('2 Central Tendency'!$B$4:$B$6,$B14,'2 Central Tendency'!$H$4:$H$6)+SUMIF('3 Dispersion'!$B$4:$B$11,$B14,'3 Dispersion'!$H$4:$H$11)+SUMIF('4 Skewness + Moments'!$B$4:$B$15,$B14,'4 Skewness + Moments'!$H$4:$H$15)+SUMIF('5 Correlation + Regression'!$B$4:$B$18,$B14,'5 Correlation + Regression'!$H$4:$H$18)
A15: 2 | B15: 2022-23 | C15: =COUNTIF('1 Intro + Graphs'!$B$4:$B$8,$B15)+COUNTIF('2 Central Tendency'!$B$4:$B$6,$B15)+COUNTIF('3 Dispersion'!$B$4:$B$11,$B15)+COUNTIF('4 Skewness + Moments'!$B$4:$B$15,$B15)+COUNTIF('5 Correlation + Regression'!$B$4:$B$18,$B15) | D15: =COUNTIFS('1 Intro + Graphs'!$B$4:$B$8,$B15,'1 Intro + Graphs'!$N$4:$N$8,TRUE())+COUNTIFS('2 Central Tendency'!$B$4:$B$6,$B15,'2 Central Tendency'!$N$4:$N$6,TRUE())+COUNTIFS('3 Dispersion'!$B$4:$B$11,$B15,'3 Dispersion'!$N$4:$N$11,TRUE())+COUNTIFS('4 Skewness + Moments'!$B$4:$B$15,$B15,'4 Skewness + Moments'!$N$4:$N$15,TRUE())+COUNTIFS('5 Correlation + Regression'!$B$4:$B$18,$B15,'5 Correlation + Regression'!$N$4:$N$18,TRUE()) | E15: =IF(C15=0,0,D15/C15) | F15: =SUMIF('1 Intro + Graphs'!$B$4:$B$8,$B15,'1 Intro + Graphs'!$H$4:$H$8)+SUMIF('2 Central Tendency'!$B$4:$B$6,$B15,'2 Central Tendency'!$H$4:$H$6)+SUMIF('3 Dispersion'!$B$4:$B$11,$B15,'3 Dispersion'!$H$4:$H$11)+SUMIF('4 Skewness + Moments'!$B$4:$B$15,$B15,'4 Skewness + Moments'!$H$4:$H$15)+SUMIF('5 Correlation + Regression'!$B$4:$B$18,$B15,'5 Correlation + Regression'!$H$4:$H$18)
A16: 3 | B16: 2021-22 | C16: =COUNTIF('1 Intro + Graphs'!$B$4:$B$8,$B16)+COUNTIF('2 Central Tendency'!$B$4:$B$6,$B16)+COUNTIF('3 Dispersion'!$B$4:$B$11,$B16)+COUNTIF('4 Skewness + Moments'!$B$4:$B$15,$B16)+COUNTIF('5 Correlation + Regression'!$B$4:$B$18,$B16) | D16: =COUNTIFS('1 Intro + Graphs'!$B$4:$B$8,$B16,'1 Intro + Graphs'!$N$4:$N$8,TRUE())+COUNTIFS('2 Central Tendency'!$B$4:$B$6,$B16,'2 Central Tendency'!$N$4:$N$6,TRUE())+COUNTIFS('3 Dispersion'!$B$4:$B$11,$B16,'3 Dispersion'!$N$4:$N$11,TRUE())+COUNTIFS('4 Skewness + Moments'!$B$4:$B$15,$B16,'4 Skewness + Moments'!$N$4:$N$15,TRUE())+COUNTIFS('5 Correlation + Regression'!$B$4:$B$18,$B16,'5 Correlation + Regression'!$N$4:$N$18,TRUE()) | E16: =IF(C16=0,0,D16/C16) | F16: =SUMIF('1 Intro + Graphs'!$B$4:$B$8,$B16,'1 Intro + Graphs'!$H$4:$H$8)+SUMIF('2 Central Tendency'!$B$4:$B$6,$B16,'2 Central Tendency'!$H$4:$H$6)+SUMIF('3 Dispersion'!$B$4:$B$11,$B16,'3 Dispersion'!$H$4:$H$11)+SUMIF('4 Skewness + Moments'!$B$4:$B$15,$B16,'4 Skewness + Moments'!$H$4:$H$15)+SUMIF('5 Correlation + Regression'!$B$4:$B$18,$B16,'5 Correlation + Regression'!$H$4:$H$18)
A17: 4 | B17: 2020-21 | C17: =COUNTIF('1 Intro + Graphs'!$B$4:$B$8,$B17)+COUNTIF('2 Central Tendency'!$B$4:$B$6,$B17)+COUNTIF('3 Dispersion'!$B$4:$B$11,$B17)+COUNTIF('4 Skewness + Moments'!$B$4:$B$15,$B17)+COUNTIF('5 Correlation + Regression'!$B$4:$B$18,$B17) | D17: =COUNTIFS('1 Intro + Graphs'!$B$4:$B$8,$B17,'1 Intro + Graphs'!$N$4:$N$8,TRUE())+COUNTIFS('2 Central Tendency'!$B$4:$B$6,$B17,'2 Central Tendency'!$N$4:$N$6,TRUE())+COUNTIFS('3 Dispersion'!$B$4:$B$11,$B17,'3 Dispersion'!$N$4:$N$11,TRUE())+COUNTIFS('4 Skewness + Moments'!$B$4:$B$15,$B17,'4 Skewness + Moments'!$N$4:$N$15,TRUE())+COUNTIFS('5 Correlation + Regression'!$B$4:$B$18,$B17,'5 Correlation + Regression'!$N$4:$N$18,TRUE()) | E17: =IF(C17=0,0,D17/C17) | F17: =SUMIF('1 Intro + Graphs'!$B$4:$B$8,$B17,'1 Intro + Graphs'!$H$4:$H$8)+SUMIF('2 Central Tendency'!$B$4:$B$6,$B17,'2 Central Tendency'!$H$4:$H$6)+SUMIF('3 Dispersion'!$B$4:$B$11,$B17,'3 Dispersion'!$H$4:$H$11)+SUMIF('4 Skewness + Moments'!$B$4:$B$15,$B17,'4 Skewness + Moments'!$H$4:$H$15)+SUMIF('5 Correlation + Regression'!$B$4:$B$18,$B17,'5 Correlation + Regression'!$H$4:$H$18)
A18: 5 | B18: 2019-20 | C18: =COUNTIF('1 Intro + Graphs'!$B$4:$B$8,$B18)+COUNTIF('2 Central Tendency'!$B$4:$B$6,$B18)+COUNTIF('3 Dispersion'!$B$4:$B$11,$B18)+COUNTIF('4 Skewness + Moments'!$B$4:$B$15,$B18)+COUNTIF('5 Correlation + Regression'!$B$4:$B$18,$B18) | D18: =COUNTIFS('1 Intro + Graphs'!$B$4:$B$8,$B18,'1 Intro + Graphs'!$N$4:$N$8,TRUE())+COUNTIFS('2 Central Tendency'!$B$4:$B$6,$B18,'2 Central Tendency'!$N$4:$N$6,TRUE())+COUNTIFS('3 Dispersion'!$B$4:$B$11,$B18,'3 Dispersion'!$N$4:$N$11,TRUE())+COUNTIFS('4 Skewness + Moments'!$B$4:$B$15,$B18,'4 Skewness + Moments'!$N$4:$N$15,TRUE())+COUNTIFS('5 Correlation + Regression'!$B$4:$B$18,$B18,'5 Correlation + Regression'!$N$4:$N$18,TRUE()) | E18: =IF(C18=0,0,D18/C18) | F18: =SUMIF('1 Intro + Graphs'!$B$4:$B$8,$B18,'1 Intro + Graphs'!$H$4:$H$8)+SUMIF('2 Central Tendency'!$B$4:$B$6,$B18,'2 Central Tendency'!$H$4:$H$6)+SUMIF('3 Dispersion'!$B$4:$B$11,$B18,'3 Dispersion'!$H$4:$H$11)+SUMIF('4 Skewness + Moments'!$B$4:$B$15,$B18,'4 Skewness + Moments'!$H$4:$H$15)+SUMIF('5 Correlation + Regression'!$B$4:$B$18,$B18,'5 Correlation + Regression'!$H$4:$H$18)
A19: 6 | B19: 2018-19 | C19: =COUNTIF('1 Intro + Graphs'!$B$4:$B$8,$B19)+COUNTIF('2 Central Tendency'!$B$4:$B$6,$B19)+COUNTIF('3 Dispersion'!$B$4:$B$11,$B19)+COUNTIF('4 Skewness + Moments'!$B$4:$B$15,$B19)+COUNTIF('5 Correlation + Regression'!$B$4:$B$18,$B19) | D19: =COUNTIFS('1 Intro + Graphs'!$B$4:$B$8,$B19,'1 Intro + Graphs'!$N$4:$N$8,TRUE())+COUNTIFS('2 Central Tendency'!$B$4:$B$6,$B19,'2 Central Tendency'!$N$4:$N$6,TRUE())+COUNTIFS('3 Dispersion'!$B$4:$B$11,$B19,'3 Dispersion'!$N$4:$N$11,TRUE())+COUNTIFS('4 Skewness + Moments'!$B$4:$B$15,$B19,'4 Skewness + Moments'!$N$4:$N$15,TRUE())+COUNTIFS('5 Correlation + Regression'!$B$4:$B$18,$B19,'5 Correlation + Regression'!$N$4:$N$18,TRUE()) | E19: =IF(C19=0,0,D19/C19) | F19: =SUMIF('1 Intro + Graphs'!$B$4:$B$8,$B19,'1 Intro + Graphs'!$H$4:$H$8)+SUMIF('2 Central Tendency'!$B$4:$B$6,$B19,'2 Central Tendency'!$H$4:$H$6)+SUMIF('3 Dispersion'!$B$4:$B$11,$B19,'3 Dispersion'!$H$4:$H$11)+SUMIF('4 Skewness + Moments'!$B$4:$B$15,$B19,'4 Skewness + Moments'!$H$4:$H$15)+SUMIF('5 Correlation + Regression'!$B$4:$B$18,$B19,'5 Correlation + Regression'!$H$4:$H$18)
A20: 7 | B20: 2016-17 | C20: =COUNTIF('1 Intro + Graphs'!$B$4:$B$8,$B20)+COUNTIF('2 Central Tendency'!$B$4:$B$6,$B20)+COUNTIF('3 Dispersion'!$B$4:$B$11,$B20)+COUNTIF('4 Skewness + Moments'!$B$4:$B$15,$B20)+COUNTIF('5 Correlation + Regression'!$B$4:$B$18,$B20) | D20: =COUNTIFS('1 Intro + Graphs'!$B$4:$B$8,$B20,'1 Intro + Graphs'!$N$4:$N$8,TRUE())+COUNTIFS('2 Central Tendency'!$B$4:$B$6,$B20,'2 Central Tendency'!$N$4:$N$6,TRUE())+COUNTIFS('3 Dispersion'!$B$4:$B$11,$B20,'3 Dispersion'!$N$4:$N$11,TRUE())+COUNTIFS('4 Skewness + Moments'!$B$4:$B$15,$B20,'4 Skewness + Moments'!$N$4:$N$15,TRUE())+COUNTIFS('5 Correlation + Regression'!$B$4:$B$18,$B20,'5 Correlation + Regression'!$N$4:$N$18,TRUE()) | E20: =IF(C20=0,0,D20/C20) | F20: =SUMIF('1 Intro + Graphs'!$B$4:$B$8,$B20,'1 Intro + Graphs'!$H$4:$H$8)+SUMIF('2 Central Tendency'!$B$4:$B$6,$B20,'2 Central Tendency'!$H$4:$H$6)+SUMIF('3 Dispersion'!$B$4:$B$11,$B20,'3 Dispersion'!$H$4:$H$11)+SUMIF('4 Skewness + Moments'!$B$4:$B$15,$B20,'4 Skewness + Moments'!$H$4:$H$15)+SUMIF('5 Correlation + Regression'!$B$4:$B$18,$B20,'5 Correlation + Regression'!$H$4:$H$18)
A21: 8 | B21: 2015-16 | C21: =COUNTIF('1 Intro + Graphs'!$B$4:$B$8,$B21)+COUNTIF('2 Central Tendency'!$B$4:$B$6,$B21)+COUNTIF('3 Dispersion'!$B$4:$B$11,$B21)+COUNTIF('4 Skewness + Moments'!$B$4:$B$15,$B21)+COUNTIF('5 Correlation + Regression'!$B$4:$B$18,$B21) | D21: =COUNTIFS('1 Intro + Graphs'!$B$4:$B$8,$B21,'1 Intro + Graphs'!$N$4:$N$8,TRUE())+COUNTIFS('2 Central Tendency'!$B$4:$B$6,$B21,'2 Central Tendency'!$N$4:$N$6,TRUE())+COUNTIFS('3 Dispersion'!$B$4:$B$11,$B21,'3 Dispersion'!$N$4:$N$11,TRUE())+COUNTIFS('4 Skewness + Moments'!$B$4:$B$15,$B21,'4 Skewness + Moments'!$N$4:$N$15,TRUE())+COUNTIFS('5 Correlation + Regression'!$B$4:$B$18,$B21,'5 Correlation + Regression'!$N$4:$N$18,TRUE()) | E21: =IF(C21=0,0,D21/C21) | F21: =SUMIF('1 Intro + Graphs'!$B$4:$B$8,$B21,'1 Intro + Graphs'!$H$4:$H$8)+SUMIF('2 Central Tendency'!$B$4:$B$6,$B21,'2 Central Tendency'!$H$4:$H$6)+SUMIF('3 Dispersion'!$B$4:$B$11,$B21,'3 Dispersion'!$H$4:$H$11)+SUMIF('4 Skewness + Moments'!$B$4:$B$15,$B21,'4 Skewness + Moments'!$H$4:$H$15)+SUMIF('5 Correlation + Regression'!$B$4:$B$18,$B21,'5 Correlation + Regression'!$H$4:$H$18)
A22: 9 | B22: 2014-15 | C22: =COUNTIF('1 Intro + Graphs'!$B$4:$B$8,$B22)+COUNTIF('2 Central Tendency'!$B$4:$B$6,$B22)+COUNTIF('3 Dispersion'!$B$4:$B$11,$B22)+COUNTIF('4 Skewness + Moments'!$B$4:$B$15,$B22)+COUNTIF('5 Correlation + Regression'!$B$4:$B$18,$B22) | D22: =COUNTIFS('1 Intro + Graphs'!$B$4:$B$8,$B22,'1 Intro + Graphs'!$N$4:$N$8,TRUE())+COUNTIFS('2 Central Tendency'!$B$4:$B$6,$B22,'2 Central Tendency'!$N$4:$N$6,TRUE())+COUNTIFS('3 Dispersion'!$B$4:$B$11,$B22,'3 Dispersion'!$N$4:$N$11,TRUE())+COUNTIFS('4 Skewness + Moments'!$B$4:$B$15,$B22,'4 Skewness + Moments'!$N$4:$N$15,TRUE())+COUNTIFS('5 Correlation + Regression'!$B$4:$B$18,$B22,'5 Correlation + Regression'!$N$4:$N$18,TRUE()) | E22: =IF(C22=0,0,D22/C22) | F22: =SUMIF('1 Intro + Graphs'!$B$4:$B$8,$B22,'1 Intro + Graphs'!$H$4:$H$8)+SUMIF('2 Central Tendency'!$B$4:$B$6,$B22,'2 Central Tendency'!$H$4:$H$6)+SUMIF('3 Dispersion'!$B$4:$B$11,$B22,'3 Dispersion'!$H$4:$H$11)+SUMIF('4 Skewness + Moments'!$B$4:$B$15,$B22,'4 Skewness + Moments'!$H$4:$H$15)+SUMIF('5 Correlation + Regression'!$B$4:$B$18,$B22,'5 Correlation + Regression'!$H$4:$H$18)
A23: 10 | B23: 2013-14 | C23: =COUNTIF('1 Intro + Graphs'!$B$4:$B$8,$B23)+COUNTIF('2 Central Tendency'!$B$4:$B$6,$B23)+COUNTIF('3 Dispersion'!$B$4:$B$11,$B23)+COUNTIF('4 Skewness + Moments'!$B$4:$B$15,$B23)+COUNTIF('5 Correlation + Regression'!$B$4:$B$18,$B23) | D23: =COUNTIFS('1 Intro + Graphs'!$B$4:$B$8,$B23,'1 Intro + Graphs'!$N$4:$N$8,TRUE())+COUNTIFS('2 Central Tendency'!$B$4:$B$6,$B23,'2 Central Tendency'!$N$4:$N$6,TRUE())+COUNTIFS('3 Dispersion'!$B$4:$B$11,$B23,'3 Dispersion'!$N$4:$N$11,TRUE())+COUNTIFS('4 Skewness + Moments'!$B$4:$B$15,$B23,'4 Skewness + Moments'!$N$4:$N$15,TRUE())+COUNTIFS('5 Correlation + Regression'!$B$4:$B$18,$B23,'5 Correlation + Regression'!$N$4:$N$18,TRUE()) | E23: =IF(C23=0,0,D23/C23) | F23: =SUMIF('1 Intro + Graphs'!$B$4:$B$8,$B23,'1 Intro + Graphs'!$H$4:$H$8)+SUMIF('2 Central Tendency'!$B$4:$B$6,$B23,'2 Central Tendency'!$H$4:$H$6)+SUMIF('3 Dispersion'!$B$4:$B$11,$B23,'3 Dispersion'!$H$4:$H$11)+SUMIF('4 Skewness + Moments'!$B$4:$B$15,$B23,'4 Skewness + Moments'!$H$4:$H$15)+SUMIF('5 Correlation + Regression'!$B$4:$B$18,$B23,'5 Correlation + Regression'!$H$4:$H$18)
A24: 11 | B24: 2012-13 | C24: =COUNTIF('1 Intro + Graphs'!$B$4:$B$8,$B24)+COUNTIF('2 Central Tendency'!$B$4:$B$6,$B24)+COUNTIF('3 Dispersion'!$B$4:$B$11,$B24)+COUNTIF('4 Skewness + Moments'!$B$4:$B$15,$B24)+COUNTIF('5 Correlation + Regression'!$B$4:$B$18,$B24) | D24: =COUNTIFS('1 Intro + Graphs'!$B$4:$B$8,$B24,'1 Intro + Graphs'!$N$4:$N$8,TRUE())+COUNTIFS('2 Central Tendency'!$B$4:$B$6,$B24,'2 Central Tendency'!$N$4:$N$6,TRUE())+COUNTIFS('3 Dispersion'!$B$4:$B$11,$B24,'3 Dispersion'!$N$4:$N$11,TRUE())+COUNTIFS('4 Skewness + Moments'!$B$4:$B$15,$B24,'4 Skewness + Moments'!$N$4:$N$15,TRUE())+COUNTIFS('5 Correlation + Regression'!$B$4:$B$18,$B24,'5 Correlation + Regression'!$N$4:$N$18,TRUE()) | E24: =IF(C24=0,0,D24/C24) | F24: =SUMIF('1 Intro + Graphs'!$B$4:$B$8,$B24,'1 Intro + Graphs'!$H$4:$H$8)+SUMIF('2 Central Tendency'!$B$4:$B$6,$B24,'2 Central Tendency'!$H$4:$H$6)+SUMIF('3 Dispersion'!$B$4:$B$11,$B24,'3 Dispersion'!$H$4:$H$11)+SUMIF('4 Skewness + Moments'!$B$4:$B$15,$B24,'4 Skewness + Moments'!$H$4:$H$15)+SUMIF('5 Correlation + Regression'!$B$4:$B$18,$B24,'5 Correlation + Regression'!$H$4:$H$18)
A25: 12 | B25: 2011-12 | C25: =COUNTIF('1 Intro + Graphs'!$B$4:$B$8,$B25)+COUNTIF('2 Central Tendency'!$B$4:$B$6,$B25)+COUNTIF('3 Dispersion'!$B$4:$B$11,$B25)+COUNTIF('4 Skewness + Moments'!$B$4:$B$15,$B25)+COUNTIF('5 Correlation + Regression'!$B$4:$B$18,$B25) | D25: =COUNTIFS('1 Intro + Graphs'!$B$4:$B$8,$B25,'1 Intro + Graphs'!$N$4:$N$8,TRUE())+COUNTIFS('2 Central Tendency'!$B$4:$B$6,$B25,'2 Central Tendency'!$N$4:$N$6,TRUE())+COUNTIFS('3 Dispersion'!$B$4:$B$11,$B25,'3 Dispersion'!$N$4:$N$11,TRUE())+COUNTIFS('4 Skewness + Moments'!$B$4:$B$15,$B25,'4 Skewness + Moments'!$N$4:$N$15,TRUE())+COUNTIFS('5 Correlation + Regression'!$B$4:$B$18,$B25,'5 Correlation + Regression'!$N$4:$N$18,TRUE()) | E25: =IF(C25=0,0,D25/C25) | F25: =SUMIF('1 Intro + Graphs'!$B$4:$B$8,$B25,'1 Intro + Graphs'!$H$4:$H$8)+SUMIF('2 Central Tendency'!$B$4:$B$6,$B25,'2 Central Tendency'!$H$4:$H$6)+SUMIF('3 Dispersion'!$B$4:$B$11,$B25,'3 Dispersion'!$H$4:$H$11)+SUMIF('4 Skewness + Moments'!$B$4:$B$15,$B25,'4 Skewness + Moments'!$H$4:$H$15)+SUMIF('5 Correlation + Regression'!$B$4:$B$18,$B25,'5 Correlation + Regression'!$H$4:$H$18)
B26: Shaded years = ★★★ High priority (2019-20 onward).
B27: Inference questions (tests, χ², CI) are in the KKS tracker, tab 8.

Sheet 1 Intro + Graphs
A1: Decks 1.1, 1.2, 5, 6 — Data, Frequency Tables, Graphs
A2: Note file: MATH243_Stat_Intro_Graphs_Notes.docx · Solve after finishing the matching lesson. Filter Priority → ★★★ High first.
A3: Q No. | B3: Year | C3: Course | D3: Ques No. | E3: Short Question | F3: Topic (slide PDF · slides) | G3: Lesson | H3: Marks | I3: TF Page | J3: Priority | K3: Type | L3: In Notes | M3: Same Type Also In | N3: Done | O3: Confidence | P3: Date | Q3: My Notes
A4: 1 | B4: 2022-23 | C4: MATH 243 | D4: 5(a) | E4: Statistical data: meaning, how produced, why needed, sources in Bangladesh | F4: Statistics, data, sampling — 1.1 Stat L1 | G4: L1 | H4: 10 | I4: 49 | J4: ★★★ High | K4: Theory | L4: ◐ Method | M4: — | N4: FALSE
A5: 2 | B5: 2022-23 | C5: MATH 243 | D5: 5(b) | E5: Insulation thickness (60 values): frequency table by Sturges' rule; histogram and cumulative frequency graph | F5: Frequency distributions, Sturges — 1.2 Stat L2 | G5: L2 | H5: 15 | I5: 49 | J5: ★★★ High | K5: Design | L5: ✔ Solved | M5: 2021-22 5(b) | N5: FALSE
A6: 3 | B6: 2021-22 | C6: MATH 245 | D6: 5(b) | E6: (i) 34 observations 201–337, 7 classes of width 20 from 199.5: class limits and marks; (ii) same mean, SD, skewness — kurtosis | F6: Frequency distributions, Sturges — 1.2 Stat L2 | G6: L2 | H6: 17 | I6: 44 | J6: ★★★ High | K6: Theory | L6: ✔ Solved | M6: 2022-23 5(b) | N6: FALSE
A7: 4 | B7: 2023-24 | C7: MATH 243 | D7: 5(a) | E7: What is a stem-and-leaf plot; how to create one, with an example | F7: Stem-and-leaf, boxplot — Graphical 2 pp. 8–18 | G7: L4 | H7: 10 | I7: 22 batch p.3 | J7: ★★★ High | K7: Design | L7: ✔ Solved | M7: 2022-23 6(b) | N7: FALSE
A8: 5 | B8: 2022-23 | C8: MATH 243 | D8: 6(b) | E8: Lengths of 12 pencils: stem-and-leaf plot; median, mode, range | F8: Stem-and-leaf, boxplot — Graphical 2 pp. 8–18 | G8: L4 | H8: 10 | I8: 50 | J8: ★★★ High | K8: Design | L8: ✔ Solved | M8: 2023-24 5(a) | N8: FALSE

Sheet 2 Central Tendency
A1: Deck 2 — Mean, Median, Quartiles, Mode
A2: Note file: MATH243_Stat_Central_Tendency_Notes.docx · Solve after finishing the matching lesson. Filter Priority → ★★★ High first.
A3: Q No. | B3: Year | C3: Course | D3: Ques No. | E3: Short Question | F3: Topic (slide PDF · slides) | G3: Lesson | H3: Marks | I3: TF Page | J3: Priority | K3: Type | L3: In Notes | M3: Same Type Also In | N3: Done | O3: Confidence | P3: Date | Q3: My Notes
A4: 1 | B4: 2021-22 | C4: MATH 245 | D4: 5(a) | E4: Monthly wages 1900-2400 (7 classes): suitable diagram, median from graph and formula; workers earning 2000–2170 | F4: Median, quartiles, ogive — Central Tendency pp. 7–18 | G4: L6 | H4: 18 | I4: 44 | J4: ★★★ High | K4: Numerical | L4: ✔ Solved | M4: — | N4: FALSE
A5: 2 | B5: 2015-16 | C5: MATH 241 | D5: 6(a) | E5: Incomplete distribution, N = 1000, median 415: missing frequencies, modal value, shape | F5: Mode, missing frequencies — Central Tendency pp. 19–26 | G5: L7 | H5: 18 | I5: 15 | J5: ★★ Medium | K5: Numerical | L5: ✔ Solved | M5: 2014-15 6(a) | N5: FALSE
A6: 3 | B6: 2014-15 | C6: MATH 241 | D6: 6(a) | E6: Incomplete distribution, N = 1000, median 413.11: find the two missing frequencies and the mode | F6: Mode, missing frequencies — Central Tendency pp. 19–26 | G6: L7 | H6: 17 | I6: 10 | J6: ★★ Medium | K6: Numerical | L6: ✔ Solved | M6: 2015-16 6(a) | N6: FALSE

Sheet 3 Dispersion
A1: Deck 3 — Range, QD, MD, SD, CV
A2: Note file: MATH243_Stat_Dispersion_Notes.docx · Solve after finishing the matching lesson. Filter Priority → ★★★ High first.
A3: Q No. | B3: Year | C3: Course | D3: Ques No. | E3: Short Question | F3: Topic (slide PDF · slides) | G3: Lesson | H3: Marks | I3: TF Page | J3: Priority | K3: Type | L3: In Notes | M3: Same Type Also In | N3: Done | O3: Confidence | P3: Date | Q3: My Notes
A4: 1 | B4: 2023-24 | C4: MATH 243 | D4: 5(c) | E4: Mean 60, SD 20 of 200 items; 3 and 67 taken instead of 13 and 17: corrected mean, SD, CV | F4: SD, CV, consistency — Dispersion pp. 9–23 | G4: L9 | H4: 12 | I4: 22 batch p.3 | J4: ★★★ High | K4: Numerical | L4: ✔ Solved | M4: — | N4: FALSE
A5: 2 | B5: 2022-23 | C5: MATH 243 | D5: 5(c) | E5: Bulb lives, companies A and B (grouped): which company's bulbs to prefer | F5: SD, CV, consistency — Dispersion pp. 9–23 | G5: L9 | H5: 10 | I5: 49 | J5: ★★★ High | K5: Numerical | L5: ✔ Solved | M5: 2020-21 5(a); 2019-20 5(a); 2018-19 5(a); 2015-16 6(b); 2013-14 6(a); 2011-12 6(b) | N5: FALSE
A6: 3 | B6: 2020-21 | C6: MATH 245 | D6: 5(a) | E6: Daily wages of factories A and B (grouped): higher average wage; greater variability | F6: SD, CV, consistency — Dispersion pp. 9–23 | G6: L9 | H6: 10 | I6: 37 | J6: ★★★ High | K6: Numerical | L6: ✔ Solved | M6: 2022-23 5(c); 2019-20 5(a); 2018-19 5(a); 2015-16 6(b); 2013-14 6(a); 2011-12 6(b) | N6: FALSE
A7: 4 | B7: 2019-20 | C7: MATH 245 | D7: 5(a) | E7: Coefficient of variation, profits 20-30…90-100 (f 4, 8, 18, 30, 15, 10, 8, 7) | F7: SD, CV, consistency — Dispersion pp. 9–23 | G7: L9 | H7: 10 | I7: 34 | J7: ★★★ High | K7: Numerical | L7: ✔ Solved | M7: 2022-23 5(c); 2020-21 5(a); 2018-19 5(a); 2015-16 6(b); 2013-14 6(a); 2011-12 6(b) | N7: FALSE
A8: 5 | B8: 2018-19 | C8: MATH 245 | D8: 5(a) | E8: Shares A, B, C (average price, SD, current price): which is more stable; which to dispose of | F8: SD, CV, consistency — Dispersion pp. 9–23 | G8: L9 | H8: 15 | I8: 24 | J8: ★★ Medium | K8: Numerical | L8: ✔ Solved | M8: 2022-23 5(c); 2020-21 5(a); 2019-20 5(a); 2015-16 6(b); 2013-14 6(a); 2011-12 6(b) | N8: FALSE
A9: 6 | B9: 2015-16 | C9: MATH 241 | D9: 6(b) | E9: Marks of students X and Y in 10 weeks: who is the better scorer, who is more consistent | F9: SD, CV, consistency — Dispersion pp. 9–23 | G9: L9 | H9: 17 | I9: 15 | J9: ★★ Medium | K9: Numerical | L9: ✔ Solved | M9: 2022-23 5(c); 2020-21 5(a); 2019-20 5(a); 2018-19 5(a); 2013-14 6(a); 2011-12 6(b) | N9: FALSE
A10: 7 | B10: 2013-14 | C10: MATH 241 | D10: 6(a) | E10: Lives of refrigerator models A and B (grouped): which model has greater uniformity | F10: SD, CV, consistency — Dispersion pp. 9–23 | G10: L9 | H10: 15 | I10: 7 | J10: ★★ Medium | K10: Numerical | L10: ✔ Solved | M10: 2022-23 5(c); 2020-21 5(a); 2019-20 5(a); 2018-19 5(a); 2015-16 6(b); 2011-12 6(b) | N10: FALSE
A11: 8 | B11: 2011-12 | C11: MATH 241 | D11: 6(b) | E11: Time study, samples A and B of 7 workers: which is more variable, which takes less time on average | F11: SD, CV, consistency — Dispersion pp. 9–23 | G11: L9 | H11: 15 | I11: 2 | J11: ★★ Medium | K11: Numerical | L11: ✔ Solved | M11: 2022-23 5(c); 2020-21 5(a); 2019-20 5(a); 2018-19 5(a); 2015-16 6(b); 2013-14 6(a) | N11: FALSE

Sheet 4 Skewness + Moments
A1: Deck 4 — Skewness, Moments and Kurtosis
A2: Note file: MATH243_Stat_Skewness_Moments_Kurtosis_Notes.docx · Solve after finishing the matching lesson. Filter Priority → ★★★ High first.
A3: Q No. | B3: Year | C3: Course | D3: Ques No. | E3: Short Question | F3: Topic (slide PDF · slides) | G3: Lesson | H3: Marks | I3: TF Page | J3: Priority | K3: Type | L3: In Notes | M3: Same Type Also In | N3: Done | O3: Confidence | P3: Date | Q3: My Notes
A4: 1 | B4: 2020-21 | C4: MATH 245 | D4: 5(b) | E4: Weights 30-40…80-90 (f 18, 37, 45, 27, 15, 8): Bowley's and Kelly's skewness; merits and drawbacks | F4: Pearson/Bowley/Kelly skewness — Skewness pp. 1–7 | G4: L10 | H4: 15 | I4: 37 | J4: ★★★ High | K4: Numerical | L4: ✔ Solved | M4: — | N4: FALSE
A5: 2 | B5: 2012-13 | C5: MATH 241 | D5: 6(a) | E5: Runs of players A and B in 10 matches: Pearson's skewness, kurtosis and Bowley's skewness for B; who is more consistent | F5: Pearson/Bowley/Kelly skewness — Skewness pp. 1–7 | G5: L10 | H5: 15 | I5: 5 | J5: ★ Low | K5: Numerical | L5: ✔ Solved | M5: — | N5: FALSE
A6: 3 | B6: 2023-24 | C6: MATH 243 | D6: 6(a) | E6: Marks 0-10…60-70 (f 8, 12, 20, 30, 15, 10, 5): four central moments, β1, β2; comment | F6: Moments, β1, β2, kurtosis — Skewness pp. 8–15 | G6: L11 | H6: 13 | I6: 22 batch p.3 | J6: ★★★ High | K6: Numerical | L6: ✔ Solved | M6: 2022-23 6(c); 2019-20 5(b); 2018-19 5(b); 2016-17 6(a); 2015-16 7(a); 2014-15 6(b); 2013-14 6(b); 2011-12 6(a) | N6: FALSE
A7: 4 | B7: 2022-23 | C7: MATH 243 | D7: 6(a) | E7: Define and illustrate SD, variance, skewness, kurtosis, moments | F7: Moments, β1, β2, kurtosis — Skewness pp. 8–15 | G7: L11 | H7: 10 | I7: 50 | J7: ★★★ High | K7: Theory | L7: ◐ Method | M7: — | N7: FALSE
A8: 5 | B8: 2022-23 | C8: MATH 243 | D8: 6(c) | E8: Profits 10-20…50-60 (f 18, 20, 30, 22, 10): four moments about assumed mean → about mean; γ1, γ2 | F8: Moments, β1, β2, kurtosis — Skewness pp. 8–15 | G8: L11 | H8: 15 | I8: 50 | J8: ★★★ High | K8: Numerical | L8: ✔ Solved | M8: 2023-24 6(a); 2019-20 5(b); 2018-19 5(b); 2016-17 6(a); 2015-16 7(a); 2014-15 6(b); 2013-14 6(b); 2011-12 6(a) | N8: FALSE
A9: 6 | B9: 2019-20 | C9: MATH 245 | D9: 5(b) | E9: Earnings 50-70…170-190 (f 4, 8, 12, 20, 6, 7, 3): four moments about assumed mean → about mean; γ1, γ2 | F9: Moments, β1, β2, kurtosis — Skewness pp. 8–15 | G9: L11 | H9: 25 | I9: 34 | J9: ★★★ High | K9: Numerical | L9: ✔ Solved | M9: 2023-24 6(a); 2022-23 6(c); 2018-19 5(b); 2016-17 6(a); 2015-16 7(a); 2014-15 6(b); 2013-14 6(b); 2011-12 6(a) | N9: FALSE
A10: 7 | B10: 2018-19 | C10: MATH 245 | D10: 5(b) | E10: What are skewness and kurtosis? γ1 and γ2, classes 10-20…50-60 (f 18, 20, 30, 22, 10) | F10: Moments, β1, β2, kurtosis — Skewness pp. 8–15 | G10: L11 | H10: 20 | I10: 24 | J10: ★★ Medium | K10: Numerical | L10: ✔ Solved | M10: 2023-24 6(a); 2022-23 6(c); 2019-20 5(b); 2016-17 6(a); 2015-16 7(a); 2014-15 6(b); 2013-14 6(b); 2011-12 6(a) | N10: FALSE
A11: 8 | B11: 2016-17 | C11: MATH 245 | D11: 6(a) | E11: Define skewness and kurtosis; coefficients by moments, profits 10-20…50-60 (f 18, 20, 30, 22, 10) | F11: Moments, β1, β2, kurtosis — Skewness pp. 8–15 | G11: L11 | H11: 17 | I11: 20 | J11: ★★ Medium | K11: Numerical | L11: ✔ Solved | M11: 2023-24 6(a); 2022-23 6(c); 2019-20 5(b); 2018-19 5(b); 2015-16 7(a); 2014-15 6(b); 2013-14 6(b); 2011-12 6(a) | N11: FALSE
A12: 9 | B12: 2015-16 | C12: MATH 241 | D12: 7(a) | E12: Coefficients of skewness and kurtosis, classes 10-20…50-60 (f 174, 86, 32, 181, 27); comment | F12: Moments, β1, β2, kurtosis — Skewness pp. 8–15 | G12: L11 | H12: 18 | I12: 15 | J12: ★★ Medium | K12: Numerical | L12: ✔ Solved | M12: 2023-24 6(a); 2022-23 6(c); 2019-20 5(b); 2018-19 5(b); 2016-17 6(a); 2014-15 6(b); 2013-14 6(b); 2011-12 6(a) | N12: FALSE
A13: 10 | B13: 2014-15 | C13: MATH 241 | D13: 6(b) | E13: Karl Pearson's skewness and β1, β2, classes 10-20…50-60 (f 18, 20, 30, 22, 10) | F13: Moments, β1, β2, kurtosis — Skewness pp. 8–15 | G13: L11 | H13: 18 | I13: 10 | J13: ★★ Medium | K13: Numerical | L13: ✔ Solved | M13: 2023-24 6(a); 2022-23 6(c); 2019-20 5(b); 2018-19 5(b); 2016-17 6(a); 2015-16 7(a); 2013-14 6(b); 2011-12 6(a) | N13: FALSE
A14: 11 | B14: 2013-14 | C14: MATH 241 | D14: 6(b) | E14: Coefficients of skewness and kurtosis, classes 10-20…50-60 (f 174, 86, 32, 181, 27); comment | F14: Moments, β1, β2, kurtosis — Skewness pp. 8–15 | G14: L11 | H14: 20 | I14: 7 | J14: ★★ Medium | K14: Numerical | L14: ✔ Solved | M14: 2023-24 6(a); 2022-23 6(c); 2019-20 5(b); 2018-19 5(b); 2016-17 6(a); 2015-16 7(a); 2014-15 6(b); 2011-12 6(a) | N14: FALSE
A15: 12 | B15: 2011-12 | C15: MATH 241 | D15: 6(a) | E15: Pearson's first coefficient of skewness and kurtosis, ages 21-26…51-56 (f 83, 75, 176, 130, 92, 54); comment | F15: Moments, β1, β2, kurtosis — Skewness pp. 8–15 | G15: L11 | H15: 20 | I15: 2 | J15: ★★ Medium | K15: Numerical | L15: ✔ Solved | M15: 2023-24 6(a); 2022-23 6(c); 2019-20 5(b); 2018-19 5(b); 2016-17 6(a); 2015-16 7(a); 2014-15 6(b); 2013-14 6(b) | N15: FALSE

Sheet 5 Correlation + Regression
A1: Deck 7 — Correlation and Regression Analysis
A2: Note file: MATH243_Stat_Correlation_Regression_Notes.docx · Solve after finishing the matching lesson. Filter Priority → ★★★ High first.
A3: Q No. | B3: Year | C3: Course | D3: Ques No. | E3: Short Question | F3: Topic (slide PDF · slides) | G3: Lesson | H3: Marks | I3: TF Page | J3: Priority | K3: Type | L3: In Notes | M3: Same Type Also In | N3: Done | O3: Confidence | P3: Date | Q3: My Notes
A4: 1 | B4: 2023-24 | C4: MATH 243 | D4: 5(b) | E4: Scatter plot of price vs rating for 5 restaurants; is there a relationship? | F4: Correlation, scatter — Correlation pp. 1–5 | G4: L12 | H4: 13 | I4: 22 batch p.3 | J4: ★★★ High | K4: Design | L4: ✔ Solved | M4: — | N4: FALSE
A5: 2 | B5: 2023-24 | C5: MATH 243 | D5: 4(b) | E5: Pearson's r; rank correlation with repeated ranks — sales and expenses of 10 stores | F5: Rank correlation — Correlation pp. 5–7 | G5: L13 | H5: 12 | I5: 22 batch p.2 | J5: ★★★ High | K5: Numerical | L5: ✔ Solved | M5: 2022-23 4(b) | N5: FALSE
A6: 3 | B6: 2022-23 | C6: MATH 243 | D6: 4(b) | E6: Correlation vs regression; rank correlation, Bangla vs English marks of 8 applicants (ties) | F6: Rank correlation — Correlation pp. 5–7 | G6: L13 | H6: 12 | I6: 48 | J6: ★★★ High | K6: Numerical | L6: ✔ Solved | M6: 2023-24 4(b) | N6: FALSE
A7: 4 | B7: 2022-23 | C7: MATH 243 | D7: 4(c) | E7: Ages of 10 husbands and wives: two regression equations; husband at wife 30, wife at husband 25; comment on r | F7: Regression lines — Correlation pp. 8–12 | G7: L14 | H7: 13 | I7: 49 | J7: ★★★ High | K7: Numerical | L7: ✔ Solved | M7: 2021-22 7(a); 2019-20 6(a); 2018-19 6(a); 2015-16 7(b); 2014-15 7(a); 2013-14 7(a); 2012-13 7(a); 2011-12 7(a) | N7: FALSE
A8: 5 | B8: 2021-22 | C8: MATH 245 | D8: 7(a) | E8: Loblolly pines (15): specific gravity vs modulus of rupture — both regression coefficients; r and interpretation | F8: Regression lines — Correlation pp. 8–12 | G8: L14 | H8: 20 | I8: 44–45 | J8: ★★★ High | K8: Numerical | L8: ✔ Solved | M8: 2022-23 4(c); 2019-20 6(a); 2018-19 6(a); 2015-16 7(b); 2014-15 7(a); 2013-14 7(a); 2012-13 7(a); 2011-12 7(a) | N8: FALSE
A9: 6 | B9: 2019-20 | C9: MATH 245 | D9: 6(a) | E9: Distance to transmitter vs signal strength (10 pairs): regression of Y on X; predict at 10 m | F9: Regression lines — Correlation pp. 8–12 | G9: L14 | H9: 17 | I9: 34 | J9: ★★★ High | K9: Numerical | L9: ✔ Solved | M9: 2022-23 4(c); 2021-22 7(a); 2018-19 6(a); 2015-16 7(b); 2014-15 7(a); 2013-14 7(a); 2012-13 7(a); 2011-12 7(a) | N9: FALSE
A10: 7 | B10: 2018-19 | C10: MATH 245 | D10: 6(a) | E10: Regression of capacity utilisation on production from means, SDs and r = 0.62; production when capacity is 70 | F10: Regression lines — Correlation pp. 8–12 | G10: L14 | H10: 20 | I10: 24 | J10: ★★ Medium | K10: Numerical | L10: ✔ Solved | M10: 2022-23 4(c); 2021-22 7(a); 2019-20 6(a); 2015-16 7(b); 2014-15 7(a); 2013-14 7(a); 2012-13 7(a); 2011-12 7(a) | N10: FALSE
A11: 8 | B11: 2015-16 | C11: MATH 241 | D11: 7(b) | E11: Years of service vs income (9 persons): regression equations, r; starting income for 15 years' service | F11: Regression lines — Correlation pp. 8–12 | G11: L14 | H11: 17 | I11: 16 | J11: ★★ Medium | K11: Numerical | L11: ✔ Solved | M11: 2022-23 4(c); 2021-22 7(a); 2019-20 6(a); 2018-19 6(a); 2014-15 7(a); 2013-14 7(a); 2012-13 7(a); 2011-12 7(a) | N11: FALSE
A12: 9 | B12: 2014-15 | C12: MATH 241 | D12: 7(a) | E12: Regression lines Y on X and X on Y and r (7 pairs, X 42…66, Y 56…51) | F12: Regression lines — Correlation pp. 8–12 | G12: L14 | H12: 20 | I12: 11 | J12: ★★ Medium | K12: Numerical | L12: ✔ Solved | M12: 2022-23 4(c); 2021-22 7(a); 2019-20 6(a); 2018-19 6(a); 2015-16 7(b); 2013-14 7(a); 2012-13 7(a); 2011-12 7(a) | N12: FALSE
A13: 10 | B13: 2013-14 | C13: MATH 241 | D13: 7(a) | E13: Ages of husbands and wives (8 couples): two regression equations, r; husband's age when wife is 24 | F13: Regression lines — Correlation pp. 8–12 | G13: L14 | H13: 20 | I13: 8 | J13: ★★ Medium | K13: Numerical | L13: ✔ Solved | M13: 2022-23 4(c); 2021-22 7(a); 2019-20 6(a); 2018-19 6(a); 2015-16 7(b); 2014-15 7(a); 2012-13 7(a); 2011-12 7(a) | N13: FALSE
A14: 11 | B14: 2012-13 | C14: MATH 241 | D14: 7(a) | E14: Economics vs Business marks (10 students): two regression equations and coefficients; estimates; comment on r | F14: Regression lines — Correlation pp. 8–12 | G14: L14 | H14: 18 | I14: 5 | J14: ★★ Medium | K14: Numerical | L14: ✔ Solved | M14: 2022-23 4(c); 2021-22 7(a); 2019-20 6(a); 2018-19 6(a); 2015-16 7(b); 2014-15 7(a); 2013-14 7(a); 2011-12 7(a) | N14: FALSE
A15: 12 | B15: 2011-12 | C15: MATH 241 | D15: 7(a) | E15: Two regression lines and r from 9 (X, Y) pairs (X 105…111, Y 58…55) | F15: Regression lines — Correlation pp. 8–12 | G15: L14 | H15: 20 | I15: 2 | J15: ★★ Medium | K15: Numerical | L15: ✔ Solved | M15: 2022-23 4(c); 2021-22 7(a); 2019-20 6(a); 2018-19 6(a); 2015-16 7(b); 2014-15 7(a); 2013-14 7(a); 2012-13 7(a) | N15: FALSE
A16: 13 | B16: 2023-24 | C16: MATH 243 | D16: 4(c) | E16: Objectives of correlation/regression; second-degree polynomial for nitrogen vs yield; coefficient of determination | F16: R², polynomial, multiple — Correlation pp. 12–17 | G16: L15 | H16: 12 | I16: 22 batch p.2 | J16: ★★★ High | K16: Numerical | L16: ✔ Solved | M16: 2020-21 6(a); 2016-17 6(b) | N16: FALSE
A17: 14 | B17: 2020-21 | C17: MATH 245 | D17: 6(a) | E17: Experience X vs rating Y (5 persons): fit Y on X; SSR and SST | F17: R², polynomial, multiple — Correlation pp. 12–17 | G17: L15 | H17: 15 | I17: 37 | J17: ★★★ High | K17: Numerical | L17: ✔ Solved | M17: 2023-24 4(c); 2016-17 6(b) | N17: FALSE
A18: 15 | B18: 2016-17 | C18: MATH 245 | D18: 6(b) | E18: Experience X vs rating Y (5 persons): fit Y on X; SSR, SST; is the linear model adequate (R²)? | F18: R², polynomial, multiple — Correlation pp. 12–17 | G18: L15 | H18: 18 | I18: 20 | J18: ★★ Medium | K18: Numerical | L18: ✔ Solved | M18: 2023-24 4(c); 2020-21 6(a) | N18: FALSE
